ncar_jobqueue/__init__.py
ncar_jobqueue/cluster.py
ncar_jobqueue/config.py
ncar_jobqueue/ncar-jobqueue.yaml
ncar_jobqueue/util.py
tests/__init__.py
tests/test_cluster.py
tests/test_util.py
ncar_jobqueue-2021.4.14.dist-info/LICENSE
ncar_jobqueue-2021.4.14.dist-info/METADATA
ncar_jobqueue-2021.4.14.dist-info/WHEEL
ncar_jobqueue-2021.4.14.dist-info/top_level.txt
ncar_jobqueue-2021.4.14.dist-info/RECORD
