Metadata-Version: 2.1
Name: ncar-jobqueue
Version: 2021.4.14
Summary: Utilities for expanding dask-jobqueue with appropriate settings for NCAR's clusters
Home-page: https://github.com/NCAR/ncar-jobqueue
Maintainer: NCAR XDev Team
Maintainer-email: xdev@ucar.edu
License: Apache License 2.0
Project-URL: Documentation, https://github.com/NCAR/ncar-jobqueue
Project-URL: Source, https://github.com/NCAR/ncar-jobqueue
Project-URL: Tracker, https://github.com/NCAR/ncar-jobqueue
Platform: UNKNOWN
Requires-Python: >=3.6
Requires-Dist: dask-jobqueue (>=0.7.2)
